asgi_debug.py
asgi_debug-0.1.dist-info/LICENSE
asgi_debug-0.1.dist-info/METADATA
asgi_debug-0.1.dist-info/WHEEL
asgi_debug-0.1.dist-info/top_level.txt
asgi_debug-0.1.dist-info/RECORD
